.coveragerc
CHANGES
LICENSE
MANIFEST.in
README.rst
setup.cfg
setup.py
tox.ini
tinycss/__init__.py
tinycss/color3.py
tinycss/css21.py
tinycss/decoding.py
tinycss/page3.py
tinycss/parsing.py
tinycss/speedups.c
tinycss/speedups.pyx
tinycss/token_data.py
tinycss/tokenizer.py
tinycss/version.py
tinycss.egg-info/PKG-INFO
tinycss.egg-info/SOURCES.txt
tinycss.egg-info/dependency_links.txt
tinycss.egg-info/top_level.txt
tinycss/tests/__init__.py
tinycss/tests/speed.py
tinycss/tests/test_api.py
tinycss/tests/test_color3.py
tinycss/tests/test_css21.py
tinycss/tests/test_decoding.py
tinycss/tests/test_page3.py
tinycss/tests/test_tokenizer.py