Metadata-Version: 1.1
Name: tinycss
Version: 0.2
Summary: tinycss is a complete yet simple CSS parser for Python.
Home-page: http://packages.python.org/tinycss/
Author: Simon Sapin
Author-email: simon.sapin@exyr.org
License: BSD
Platform: UNKNOWN
Classifier: Development Status :: 3 - Alpha
Classifier: Intended Audience :: Developers
Classifier: License :: OSI Approved :: BSD License
Classifier: Programming Language :: Python :: 2
Classifier: Programming Language :: Python :: 2.6
Classifier: Programming Language :: Python :: 2.7
Classifier: Programming Language :: Python :: 3
Classifier: Programming Language :: Python :: 3.1
Classifier: Programming Language :: Python :: 3.2
